dhparkeren/__init__.py
dhparkeren/account.py
dhparkeren/client.py
dhparkeren/config.py
dhparkeren/favorites.py
dhparkeren/logging.py
dhparkeren/reservations.py
dhparkeren/session.py
dhparkeren/validators.py
dhparkeren-0.1.0.dist-info/LICENSE
dhparkeren-0.1.0.dist-info/METADATA
dhparkeren-0.1.0.dist-info/WHEEL
dhparkeren-0.1.0.dist-info/RECORD
