Metadata-Version: 2.3
Name: dhparkeren
Version: 0.1.0
Summary: The Hague Visitor Parking API
Author: sir-Unknown
Author-email: sir-Unknown@users.noreply.github.com
Requires-Python: >=3.12
Classifier: Programming Language :: Python :: 3
Classifier: Programming Language :: Python :: 3.12
Classifier: Programming Language :: Python :: 3.13
Requires-Dist: aiohttp (>=3.11.12,<4.0.0)
Requires-Dist: asyncio (>=3.4.3,<4.0.0)
Requires-Dist: datetime (>=5.5,<6.0)
Requires-Dist: logging (>=0.4.9.6,<0.5.0.0)
